flapjack/__init__.py
flapjack/__version__.py
flapjack/commands.py
flapjack/config.py
flapjack/ext.py
flapjack/json_minify.py
flapjack/main.py
flapjack/state.py
flapjack/util.py
flapjack-0.1.5.dist-info/METADATA
flapjack-0.1.5.dist-info/RECORD
flapjack-0.1.5.dist-info/WHEEL
flapjack-0.1.5.dist-info/entry_points.txt
flapjack-0.1.5.dist-info/top_level.txt
