Metadata-Version: 2.1
Name: flapjack
Version: 0.1.5
Summary: Tool for developing components inside a flatpak runtime
Home-page: https://github.com/endlessm/flapjack
Author: Philip Chimento
Author-email: philip@endlessm.com
License: ISC
Platform: UNKNOWN
Classifier: Development Status :: 4 - Beta
Classifier: Environment :: Console
Classifier: Intended Audience :: Developers
Classifier: License :: OSI Approved :: GNU General Public License v2 or later (GPLv2+)
Classifier: Operating System :: POSIX :: Linux
Classifier: Programming Language :: Python
Classifier: Programming Language :: Python :: 3 :: Only
Classifier: Programming Language :: Python :: 3.4
Classifier: Programming Language :: Python :: 3.5
Classifier: Programming Language :: Python :: 3.6
Classifier: Topic :: Software Development :: Build Tools
